<annotation>
	<folder>train</folder>
	<filename>191.jpg</filename>
	<path>D:/tensorflow1/models/research/object_detection/images/train/191.jpg</path>
	<source>
		<database>Unknown</database>
	</source>
	<size>
		<width>1024</width>
		<height>600</height>
		<depth>3</depth>
	</size>
	<segmented>0</segmented>
	<object>
		<name>bird</name>
		<pose>Unspecified</pose>
		<truncated>0</truncated>
		<difficult>0</difficult>
		<bndbox>
			<xmin>639</xmin>
			<ymin>57</ymin>
			<xmax>704</xmax>
			<ymax>82</ymax>
		</bndbox>
	</object>
	<object>
		<name>bird</name>
		<pose>Unspecified</pose>
		<truncated>0</truncated>
		<difficult>0</difficult>
		<bndbox>
			<xmin>766</xmin>
			<ymin>66</ymin>
			<xmax>815</xmax>
			<ymax>91</ymax>
		</bndbox>
	</object>
	<object>
		<name>bird</name>
		<pose>Unspecified</pose>
		<truncated>0</truncated>
		<difficult>0</difficult>
		<bndbox>
			<xmin>824</xmin>
			<ymin>47</ymin>
			<xmax>883</xmax>
			<ymax>74</ymax>
		</bndbox>
	</object>
	<object>
		<name>bird</name>
		<pose>Unspecified</pose>
		<truncated>0</truncated>
		<difficult>0</difficult>
		<bndbox>
			<xmin>914</xmin>
			<ymin>99</ymin>
			<xmax>970</xmax>
			<ymax>115</ymax>
		</bndbox>
	</object>
	<object>
		<name>bird</name>
		<pose>Unspecified</pose>
		<truncated>0</truncated>
		<difficult>0</difficult>
		<bndbox>
			<xmin>940</xmin>
			<ymin>20</ymin>
			<xmax>979</xmax>
			<ymax>45</ymax>
		</bndbox>
	</object>
	<object>
		<name>bird</name>
		<pose>Unspecified</pose>
		<truncated>0</truncated>
		<difficult>0</difficult>
		<bndbox>
			<xmin>893</xmin>
			<ymin>332</ymin>
			<xmax>959</xmax>
			<ymax>360</ymax>
		</bndbox>
	</object>
	<object>
		<name>bird</name>
		<pose>Unspecified</pose>
		<truncated>0</truncated>
		<difficult>0</difficult>
		<bndbox>
			<xmin>949</xmin>
			<ymin>268</ymin>
			<xmax>1017</xmax>
			<ymax>290</ymax>
		</bndbox>
	</object>
	<object>
		<name>bird</name>
		<pose>Unspecified</pose>
		<truncated>0</truncated>
		<difficult>0</difficult>
		<bndbox>
			<xmin>814</xmin>
			<ymin>327</ymin>
			<xmax>877</xmax>
			<ymax>344</ymax>
		</bndbox>
	</object>
	<object>
		<name>bird</name>
		<pose>Unspecified</pose>
		<truncated>0</truncated>
		<difficult>0</difficult>
		<bndbox>
			<xmin>751</xmin>
			<ymin>369</ymin>
			<xmax>807</xmax>
			<ymax>398</ymax>
		</bndbox>
	</object>
</annotation>
