<annotation>
	<folder>train</folder>
	<filename>422.jpg</filename>
	<path>D:/tensorflow1/models/research/object_detection/images/train/422.jpg</path>
	<source>
		<database>Unknown</database>
	</source>
	<size>
		<width>1024</width>
		<height>600</height>
		<depth>3</depth>
	</size>
	<segmented>0</segmented>
	<object>
		<name>bird</name>
		<pose>Unspecified</pose>
		<truncated>1</truncated>
		<difficult>0</difficult>
		<bndbox>
			<xmin>1</xmin>
			<ymin>83</ymin>
			<xmax>672</xmax>
			<ymax>597</ymax>
		</bndbox>
	</object>
	<object>
		<name>bird</name>
		<pose>Unspecified</pose>
		<truncated>0</truncated>
		<difficult>0</difficult>
		<bndbox>
			<xmin>72</xmin>
			<ymin>233</ymin>
			<xmax>767</xmax>
			<ymax>365</ymax>
		</bndbox>
	</object>
</annotation>
