<annotation>
	<folder>train</folder>
	<filename>472.jpg</filename>
	<path>D:/tensorflow1/models/research/object_detection/images/train/472.jpg</path>
	<source>
		<database>Unknown</database>
	</source>
	<size>
		<width>1024</width>
		<height>600</height>
		<depth>3</depth>
	</size>
	<segmented>0</segmented>
	<object>
		<name>bird</name>
		<pose>Unspecified</pose>
		<truncated>0</truncated>
		<difficult>0</difficult>
		<bndbox>
			<xmin>99</xmin>
			<ymin>56</ymin>
			<xmax>188</xmax>
			<ymax>179</ymax>
		</bndbox>
	</object>
	<object>
		<name>bird</name>
		<pose>Unspecified</pose>
		<truncated>0</truncated>
		<difficult>0</difficult>
		<bndbox>
			<xmin>535</xmin>
			<ymin>105</ymin>
			<xmax>627</xmax>
			<ymax>213</ymax>
		</bndbox>
	</object>
	<object>
		<name>bird</name>
		<pose>Unspecified</pose>
		<truncated>0</truncated>
		<difficult>0</difficult>
		<bndbox>
			<xmin>492</xmin>
			<ymin>336</ymin>
			<xmax>575</xmax>
			<ymax>452</ymax>
		</bndbox>
	</object>
	<object>
		<name>bird</name>
		<pose>Unspecified</pose>
		<truncated>0</truncated>
		<difficult>0</difficult>
		<bndbox>
			<xmin>297</xmin>
			<ymin>419</ymin>
			<xmax>378</xmax>
			<ymax>527</ymax>
		</bndbox>
	</object>
	<object>
		<name>bird</name>
		<pose>Unspecified</pose>
		<truncated>0</truncated>
		<difficult>0</difficult>
		<bndbox>
			<xmin>208</xmin>
			<ymin>465</ymin>
			<xmax>301</xmax>
			<ymax>590</ymax>
		</bndbox>
	</object>
</annotation>
